hilite_syntax/__init__.py
hilite_syntax/converter.py
hilite_syntax/inline.py
hilite_syntax/lark.py
hilite_syntax/node.py
hilite_syntax/vim.py
hilite_syntax-0.0.4.data/scripts/hilite_syntax
hilite_syntax-0.0.4.dist-info/LICENSE
hilite_syntax-0.0.4.dist-info/METADATA
hilite_syntax-0.0.4.dist-info/WHEEL
hilite_syntax-0.0.4.dist-info/top_level.txt
hilite_syntax-0.0.4.dist-info/RECORD
