Metadata-Version: 2.1
Name: hilite-syntax
Version: 0.0.4
Summary: Framework for generating editor syntax files
Home-page: https://github.com/ssteffl/python-hilite-syntax
Author: Sam Steffl
Author-email: sam@ssteffl.com
License: UNKNOWN
Project-URL: Bug Reports, https://github.com/ssteffl/python-hilite-syntax
Project-URL: Source, https://github.com/ssteffl/python-hilite-syntax
Keywords: hilite hilight syntax editor
Platform: UNKNOWN
Classifier: Development Status :: 3 - Alpha
Classifier: Intended Audience :: Developers
Classifier: Topic :: Software Development :: Libraries
Classifier: License :: OSI Approved :: MIT License
Classifier: Programming Language :: Python :: 3
Requires-Python: >=3.6
Requires-Dist: dcggraph
Requires-Dist: lark-parser
